<?xml version="1.0" encoding="UTF-8" standalone="yes"?>
<map>
    <mapBackgroundFileName>OriginalMap.png</mapBackgroundFileName>
    <Countries>
        <Country>
            <coordinate>
                <x>60</x>
                <y>80</y>
            </coordinate>
            <name>Alaska</name>
        </Country>
        <Country>
            <coordinate>
                <x>156</x>
                <y>131</y>
            </coordinate>
            <name>Alberta</name>
        </Country>
        <Country>
            <coordinate>
                <x>180</x>
                <y>287</y>
            </coordinate>
            <name>CentralAmerica</name>
        </Country>
        <Country>
            <coordinate>
                <x>247</x>
                <y>221</y>
            </coordinate>
            <name>EasternUnitedStates</name>
        </Country>
        <Country>
            <coordinate>
                <x>378</x>
                <y>52</y>
            </coordinate>
            <name>Greenland</name>
        </Country>
        <Country>
            <coordinate>
                <x>173</x>
                <y>85</y>
            </coordinate>
            <name>NorthwestTerritory</name>
        </Country>
        <Country>
            <coordinate>
                <x>237</x>
                <y>148</y>
            </coordinate>
            <name>Ontario</name>
        </Country>
        <Country>
            <coordinate>
                <x>302</x>
                <y>143</y>
            </coordinate>
            <name>Quebec</name>
        </Country>
        <Country>
            <coordinate>
                <x>160</x>
                <y>205</y>
            </coordinate>
            <name>WesternUnitedStates</name>
        </Country>
        <Country>
            <coordinate>
                <x>266</x>
                <y>500</y>
            </coordinate>
            <name>Argentina</name>
        </Country>
        <Country>
            <coordinate>
                <x>335</x>
                <y>405</y>
            </coordinate>
            <name>Brazil</name>
        </Country>
        <Country>
            <coordinate>
                <x>230</x>
                <y>405</y>
            </coordinate>
            <name>Peru</name>
        </Country>
        <Country>
            <coordinate>
                <x>260</x>
                <y>320</y>
            </coordinate>
            <name>Venezuela</name>
        </Country>
        <Country>
            <coordinate>
                <x>451</x>
                <y>181</y>
            </coordinate>
            <name>GreatBritain</name>
        </Country>
        <Country>
            <coordinate>
                <x>467</x>
                <y>119</y>
            </coordinate>
            <name>Iceland</name>
        </Country>
        <Country>
            <coordinate>
                <x>544</x>
                <y>194</y>
            </coordinate>
            <name>NorthernEurope</name>
        </Country>
        <Country>
            <coordinate>
                <x>556</x>
                <y>110</y>
            </coordinate>
            <name>Scandinavia</name>
        </Country>
        <Country>
            <coordinate>
                <x>557</x>
                <y>256</y>
            </coordinate>
            <name>SouthernEurope</name>
        </Country>
        <Country>
            <coordinate>
                <x>645</x>
                <y>167</y>
            </coordinate>
            <name>Ukraine</name>
        </Country>
        <Country>
            <coordinate>
                <x>465</x>
                <y>264</y>
            </coordinate>
            <name>WesternEurope</name>
        </Country>
        <Country>
            <coordinate>
                <x>590</x>
                <y>443</y>
            </coordinate>
            <name>Congo</name>
        </Country>
        <Country>
            <coordinate>
                <x>650</x>
                <y>417</y>
            </coordinate>
            <name>EastAfrica</name>
        </Country>
        <Country>
            <coordinate>
                <x>578</x>
                <y>339</y>
            </coordinate>
            <name>Egypt</name>
        </Country>
        <Country>
            <coordinate>
                <x>695</x>
                <y>521</y>
            </coordinate>
            <name>Madagascar</name>
        </Country>
        <Country>
            <coordinate>
                <x>489</x>
                <y>365</y>
            </coordinate>
            <name>NorthAfrica</name>
        </Country>
        <Country>
            <coordinate>
                <x>590</x>
                <y>521</y>
            </coordinate>
            <name>SouthAfrica</name>
        </Country>
        <Country>
            <coordinate>
                <x>745</x>
                <y>222</y>
            </coordinate>
            <name>Kazakhstan</name>
        </Country>
        <Country>
            <coordinate>
                <x>861</x>
                <y>260</y>
            </coordinate>
            <name>China</name>
        </Country>
        <Country>
            <coordinate>
                <x>799</x>
                <y>310</y>
            </coordinate>
            <name>India</name>
        </Country>
        <Country>
            <coordinate>
                <x>882</x>
                <y>145</y>
            </coordinate>
            <name>Irkutsk</name>
        </Country>
        <Country>
            <coordinate>
                <x>1000</x>
                <y>210</y>
            </coordinate>
            <name>Japan</name>
        </Country>
        <Country>
            <coordinate>
                <x>969</x>
                <y>101</y>
            </coordinate>
            <name>Kamchatka</name>
        </Country>
        <Country>
            <coordinate>
                <x>676</x>
                <y>308</y>
            </coordinate>
            <name>MiddleEast</name>
        </Country>
        <Country>
            <coordinate>
                <x>899</x>
                <y>195</y>
            </coordinate>
            <name>Mongolia</name>
        </Country>
        <Country>
            <coordinate>
                <x>896</x>
                <y>344</y>
            </coordinate>
            <name>Siam</name>
        </Country>
        <Country>
            <coordinate>
                <x>817</x>
                <y>108</y>
            </coordinate>
            <name>Siberia</name>
        </Country>
        <Country>
            <coordinate>
                <x>755</x>
                <y>141</y>
            </coordinate>
            <name>Ural</name>
        </Country>
        <Country>
            <coordinate>
                <x>896</x>
                <y>73</y>
            </coordinate>
            <name>Yakutsk</name>
        </Country>
        <Country>
            <coordinate>
                <x>1044</x>
                <y>520</y>
            </coordinate>
            <name>EasternAustralia</name>
        </Country>
        <Country>
            <coordinate>
                <x>913</x>
                <y>439</y>
            </coordinate>
            <name>Indonesia</name>
        </Country>
        <Country>
            <coordinate>
                <x>1003</x>
                <y>415</y>
            </coordinate>
            <name>NewGuinea</name>
        </Country>
        <Country>
            <coordinate>
                <x>952</x>
                <y>520</y>
            </coordinate>
            <name>WesternAustralia</name>
        </Country>
    </Countries>
    <Neighbours>
        <Neighbour>
            <CountrySourceID>Alberta</CountrySourceID>
            <CountryDestinationID>WesternUnitedStates</CountryDestinationID>
        </Neighbour>
        <Neighbour>
            <CountrySourceID>Alaska</CountrySourceID>
            <CountryDestinationID>NorthwestTerritory</CountryDestinationID>
        </Neighbour>
        <Neighbour>
            <CountrySourceID>Egypt</CountrySourceID>
            <CountryDestinationID>MiddleEast</CountryDestinationID>
        </Neighbour>
        <Neighbour>
            <CountrySourceID>WesternAustralia</CountrySourceID>
            <CountryDestinationID>NewGuinea</CountryDestinationID>
        </Neighbour>
        <Neighbour>
            <CountrySourceID>NorthernEurope</CountrySourceID>
            <CountryDestinationID>Ukraine</CountryDestinationID>
        </Neighbour>
        <Neighbour>
            <CountrySourceID>Congo</CountrySourceID>
            <CountryDestinationID>NorthAfrica</CountryDestinationID>
        </Neighbour>
        <Neighbour>
            <CountrySourceID>Kazakhstan</CountrySourceID>
            <CountryDestinationID>MiddleEast</CountryDestinationID>
        </Neighbour>
        <Neighbour>
            <CountrySourceID>Japan</CountrySourceID>
            <CountryDestinationID>Mongolia</CountryDestinationID>
        </Neighbour>
        <Neighbour>
            <CountrySourceID>Venezuela</CountrySourceID>
            <CountryDestinationID>Brazil</CountryDestinationID>
        </Neighbour>
        <Neighbour>
            <CountrySourceID>Kazakhstan</CountrySourceID>
            <CountryDestinationID>India</CountryDestinationID>
        </Neighbour>
        <Neighbour>
            <CountrySourceID>GreatBritain</CountrySourceID>
            <CountryDestinationID>Scandinavia</CountryDestinationID>
        </Neighbour>
        <Neighbour>
            <CountrySourceID>Greenland</CountrySourceID>
            <CountryDestinationID>Ontario</CountryDestinationID>
        </Neighbour>
        <Neighbour>
            <CountrySourceID>EastAfrica</CountrySourceID>
            <CountryDestinationID>Madagascar</CountryDestinationID>
        </Neighbour>
        <Neighbour>
            <CountrySourceID>Kazakhstan</CountrySourceID>
            <CountryDestinationID>China</CountryDestinationID>
        </Neighbour>
        <Neighbour>
            <CountrySourceID>Mongolia</CountrySourceID>
            <CountryDestinationID>Siberia</CountryDestinationID>
        </Neighbour>
        <Neighbour>
            <CountrySourceID>Ontario</CountrySourceID>
            <CountryDestinationID>Quebec</CountryDestinationID>
        </Neighbour>
        <Neighbour>
            <CountrySourceID>Indonesia</CountrySourceID>
            <CountryDestinationID>WesternAustralia</CountryDestinationID>
        </Neighbour>
        <Neighbour>
            <CountrySourceID>Irkutsk</CountrySourceID>
            <CountryDestinationID>Mongolia</CountryDestinationID>
        </Neighbour>
        <Neighbour>
            <CountrySourceID>Irkutsk</CountrySourceID>
            <CountryDestinationID>Siberia</CountryDestinationID>
        </Neighbour>
        <Neighbour>
            <CountrySourceID>Indonesia</CountrySourceID>
            <CountryDestinationID>NewGuinea</CountryDestinationID>
        </Neighbour>
        <Neighbour>
            <CountrySourceID>NorthwestTerritory</CountrySourceID>
            <CountryDestinationID>Ontario</CountryDestinationID>
        </Neighbour>
        <Neighbour>
            <CountrySourceID>Kazakhstan</CountrySourceID>
            <CountryDestinationID>Ukraine</CountryDestinationID>
        </Neighbour>
        <Neighbour>
            <CountrySourceID>China</CountrySourceID>
            <CountryDestinationID>India</CountryDestinationID>
        </Neighbour>
        <Neighbour>
            <CountrySourceID>EasternAustralia</CountrySourceID>
            <CountryDestinationID>WesternAustralia</CountryDestinationID>
        </Neighbour>
        <Neighbour>
            <CountrySourceID>GreatBritain</CountrySourceID>
            <CountryDestinationID>WesternEurope</CountryDestinationID>
        </Neighbour>
        <Neighbour>
            <CountrySourceID>Madagascar</CountrySourceID>
            <CountryDestinationID>SouthAfrica</CountryDestinationID>
        </Neighbour>
        <Neighbour>
            <CountrySourceID>Siberia</CountrySourceID>
            <CountryDestinationID>Yakutsk</CountryDestinationID>
        </Neighbour>
        <Neighbour>
            <CountrySourceID>Greenland</CountrySourceID>
            <CountryDestinationID>Iceland</CountryDestinationID>
        </Neighbour>
        <Neighbour>
            <CountrySourceID>EasternUnitedStates</CountrySourceID>
            <CountryDestinationID>WesternUnitedStates</CountryDestinationID>
        </Neighbour>
        <Neighbour>
            <CountrySourceID>EasternAustralia</CountrySourceID>
            <CountryDestinationID>NewGuinea</CountryDestinationID>
        </Neighbour>
        <Neighbour>
            <CountrySourceID>India</CountrySourceID>
            <CountryDestinationID>Siam</CountryDestinationID>
        </Neighbour>
        <Neighbour>
            <CountrySourceID>Alaska</CountrySourceID>
            <CountryDestinationID>Kamchatka</CountryDestinationID>
        </Neighbour>
        <Neighbour>
            <CountrySourceID>EasternUnitedStates</CountrySourceID>
            <CountryDestinationID>Quebec</CountryDestinationID>
        </Neighbour>
        <Neighbour>
            <CountrySourceID>Kamchatka</CountrySourceID>
            <CountryDestinationID>Yakutsk</CountryDestinationID>
        </Neighbour>
        <Neighbour>
            <CountrySourceID>Alberta</CountrySourceID>
            <CountryDestinationID>Ontario</CountryDestinationID>
        </Neighbour>
        <Neighbour>
            <CountrySourceID>GreatBritain</CountrySourceID>
            <CountryDestinationID>Iceland</CountryDestinationID>
        </Neighbour>
        <Neighbour>
            <CountrySourceID>Iceland</CountrySourceID>
            <CountryDestinationID>Scandinavia</CountryDestinationID>
        </Neighbour>
        <Neighbour>
            <CountrySourceID>EasternUnitedStates</CountrySourceID>
            <CountryDestinationID>Ontario</CountryDestinationID>
        </Neighbour>
        <Neighbour>
            <CountrySourceID>Ontario</CountrySourceID>
            <CountryDestinationID>WesternUnitedStates</CountryDestinationID>
        </Neighbour>
        <Neighbour>
            <CountrySourceID>Irkutsk</CountrySourceID>
            <CountryDestinationID>Kamchatka</CountryDestinationID>
        </Neighbour>
        <Neighbour>
            <CountrySourceID>Congo</CountrySourceID>
            <CountryDestinationID>SouthAfrica</CountryDestinationID>
        </Neighbour>
        <Neighbour>
            <CountrySourceID>Japan</CountrySourceID>
            <CountryDestinationID>Kamchatka</CountryDestinationID>
        </Neighbour>
        <Neighbour>
            <CountrySourceID>SouthernEurope</CountrySourceID>
            <CountryDestinationID>WesternEurope</CountryDestinationID>
        </Neighbour>
        <Neighbour>
            <CountrySourceID>EastAfrica</CountrySourceID>
            <CountryDestinationID>NorthAfrica</CountryDestinationID>
        </Neighbour>
        <Neighbour>
            <CountrySourceID>EastAfrica</CountrySourceID>
            <CountryDestinationID>SouthAfrica</CountryDestinationID>
        </Neighbour>
        <Neighbour>
            <CountrySourceID>MiddleEast</CountrySourceID>
            <CountryDestinationID>SouthernEurope</CountryDestinationID>
        </Neighbour>
        <Neighbour>
            <CountrySourceID>Indonesia</CountrySourceID>
            <CountryDestinationID>Siam</CountryDestinationID>
        </Neighbour>
        <Neighbour>
            <CountrySourceID>Congo</CountrySourceID>
            <CountryDestinationID>EastAfrica</CountryDestinationID>
        </Neighbour>
        <Neighbour>
            <CountrySourceID>EastAfrica</CountrySourceID>
            <CountryDestinationID>MiddleEast</CountryDestinationID>
        </Neighbour>
        <Neighbour>
            <CountrySourceID>NorthernEurope</CountrySourceID>
            <CountryDestinationID>Scandinavia</CountryDestinationID>
        </Neighbour>
        <Neighbour>
            <CountrySourceID>Alaska</CountrySourceID>
            <CountryDestinationID>Alberta</CountryDestinationID>
        </Neighbour>
        <Neighbour>
            <CountrySourceID>Venezuela</CountrySourceID>
            <CountryDestinationID>Peru</CountryDestinationID>
        </Neighbour>
        <Neighbour>
            <CountrySourceID>NorthAfrica</CountrySourceID>
            <CountryDestinationID>SouthernEurope</CountryDestinationID>
        </Neighbour>
        <Neighbour>
            <CountrySourceID>GreatBritain</CountrySourceID>
            <CountryDestinationID>NorthernEurope</CountryDestinationID>
        </Neighbour>
        <Neighbour>
            <CountrySourceID>Alberta</CountrySourceID>
            <CountryDestinationID>NorthwestTerritory</CountryDestinationID>
        </Neighbour>
        <Neighbour>
            <CountrySourceID>Kamchatka</CountrySourceID>
            <CountryDestinationID>Mongolia</CountryDestinationID>
        </Neighbour>
        <Neighbour>
            <CountrySourceID>NorthernEurope</CountrySourceID>
            <CountryDestinationID>SouthernEurope</CountryDestinationID>
        </Neighbour>
        <Neighbour>
            <CountrySourceID>Peru</CountrySourceID>
            <CountryDestinationID>Brazil</CountryDestinationID>
        </Neighbour>
        <Neighbour>
            <CountrySourceID>Egypt</CountrySourceID>
            <CountryDestinationID>NorthAfrica</CountryDestinationID>
        </Neighbour>
        <Neighbour>
            <CountrySourceID>CentralAmerica</CountrySourceID>
            <CountryDestinationID>WesternUnitedStates</CountryDestinationID>
        </Neighbour>
        <Neighbour>
            <CountrySourceID>Brazil</CountrySourceID>
            <CountryDestinationID>NorthAfrica</CountryDestinationID>
        </Neighbour>
        <Neighbour>
            <CountrySourceID>China</CountrySourceID>
            <CountryDestinationID>Siam</CountryDestinationID>
        </Neighbour>
        <Neighbour>
            <CountrySourceID>SouthernEurope</CountrySourceID>
            <CountryDestinationID>Ukraine</CountryDestinationID>
        </Neighbour>
        <Neighbour>
            <CountrySourceID>Scandinavia</CountrySourceID>
            <CountryDestinationID>Ukraine</CountryDestinationID>
        </Neighbour>
        <Neighbour>
            <CountrySourceID>Peru</CountrySourceID>
            <CountryDestinationID>Argentina</CountryDestinationID>
        </Neighbour>
        <Neighbour>
            <CountrySourceID>Siberia</CountrySourceID>
            <CountryDestinationID>Ural</CountryDestinationID>
        </Neighbour>
        <Neighbour>
            <CountrySourceID>Ural</CountrySourceID>
            <CountryDestinationID>Ukraine</CountryDestinationID>
        </Neighbour>
        <Neighbour>
            <CountrySourceID>NorthernEurope</CountrySourceID>
            <CountryDestinationID>WesternEurope</CountryDestinationID>
        </Neighbour>
        <Neighbour>
            <CountrySourceID>Greenland</CountrySourceID>
            <CountryDestinationID>NorthwestTerritory</CountryDestinationID>
        </Neighbour>
        <Neighbour>
            <CountrySourceID>Greenland</CountrySourceID>
            <CountryDestinationID>Quebec</CountryDestinationID>
        </Neighbour>
        <Neighbour>
            <CountrySourceID>Kazakhstan</CountrySourceID>
            <CountryDestinationID>Ural</CountryDestinationID>
        </Neighbour>
        <Neighbour>
            <CountrySourceID>Brazil</CountrySourceID>
            <CountryDestinationID>Argentina</CountryDestinationID>
        </Neighbour>
        <Neighbour>
            <CountrySourceID>China</CountrySourceID>
            <CountryDestinationID>Siberia</CountryDestinationID>
        </Neighbour>
        <Neighbour>
            <CountrySourceID>CentralAmerica</CountrySourceID>
            <CountryDestinationID>Venezuela</CountryDestinationID>
        </Neighbour>
        <Neighbour>
            <CountrySourceID>China</CountrySourceID>
            <CountryDestinationID>Ural</CountryDestinationID>
        </Neighbour>
        <Neighbour>
            <CountrySourceID>Irkutsk</CountrySourceID>
            <CountryDestinationID>Yakutsk</CountryDestinationID>
        </Neighbour>
        <Neighbour>
            <CountrySourceID>NorthAfrica</CountrySourceID>
            <CountryDestinationID>WesternEurope</CountryDestinationID>
        </Neighbour>
        <Neighbour>
            <CountrySourceID>Egypt</CountrySourceID>
            <CountryDestinationID>SouthernEurope</CountryDestinationID>
        </Neighbour>
        <Neighbour>
            <CountrySourceID>China</CountrySourceID>
            <CountryDestinationID>Mongolia</CountryDestinationID>
        </Neighbour>
        <Neighbour>
            <CountrySourceID>EastAfrica</CountrySourceID>
            <CountryDestinationID>Egypt</CountryDestinationID>
        </Neighbour>
        <Neighbour>
            <CountrySourceID>India</CountrySourceID>
            <CountryDestinationID>MiddleEast</CountryDestinationID>
        </Neighbour>
        <Neighbour>
            <CountrySourceID>MiddleEast</CountrySourceID>
            <CountryDestinationID>Ukraine</CountryDestinationID>
        </Neighbour>
        <Neighbour>
            <CountrySourceID>CentralAmerica</CountrySourceID>
            <CountryDestinationID>EasternUnitedStates</CountryDestinationID>
        </Neighbour>
    </Neighbours>
    <Continents>
        <Continent>
            <continentName>NorthAmerica</continentName>
            <bonusForHoldingContinent>5</bonusForHoldingContinent>
            <countries>
                <CountryID>Alaska</CountryID>
                <CountryID>Alberta</CountryID>
                <CountryID>CentralAmerica</CountryID>
                <CountryID>EasternUnitedStates</CountryID>
                <CountryID>Greenland</CountryID>
                <CountryID>NorthwestTerritory</CountryID>
                <CountryID>Ontario</CountryID>
                <CountryID>Quebec</CountryID>
                <CountryID>WesternUnitedStates</CountryID>
            </countries>
        </Continent>
        <Continent>
            <continentName>Africa</continentName>
            <bonusForHoldingContinent>3</bonusForHoldingContinent>
            <countries>
                <CountryID>Congo</CountryID>
                <CountryID>EastAfrica</CountryID>
                <CountryID>Egypt</CountryID>
                <CountryID>Madagascar</CountryID>
                <CountryID>NorthAfrica</CountryID>
                <CountryID>SouthAfrica</CountryID>
            </countries>
        </Continent>
        <Continent>
            <continentName>SouthAmerica</continentName>
            <bonusForHoldingContinent>2</bonusForHoldingContinent>
            <countries>
                <CountryID>Argentina</CountryID>
                <CountryID>Brazil</CountryID>
                <CountryID>Peru</CountryID>
                <CountryID>Venezuela</CountryID>
            </countries>
        </Continent>
        <Continent>
            <continentName>Europe</continentName>
            <bonusForHoldingContinent>5</bonusForHoldingContinent>
            <countries>
                <CountryID>GreatBritain</CountryID>
                <CountryID>Iceland</CountryID>
                <CountryID>NorthernEurope</CountryID>
                <CountryID>Scandinavia</CountryID>
                <CountryID>SouthernEurope</CountryID>
                <CountryID>Ukraine</CountryID>
                <CountryID>WesternEurope</CountryID>
            </countries>
        </Continent>
        <Continent>
            <continentName>Asia</continentName>
            <bonusForHoldingContinent>7</bonusForHoldingContinent>
            <countries>
                <CountryID>Kazakhstan</CountryID>
                <CountryID>China</CountryID>
                <CountryID>India</CountryID>
                <CountryID>Irkutsk</CountryID>
                <CountryID>Japan</CountryID>
                <CountryID>Kamchatka</CountryID>
                <CountryID>MiddleEast</CountryID>
                <CountryID>Mongolia</CountryID>
                <CountryID>Siam</CountryID>
                <CountryID>Siberia</CountryID>
                <CountryID>Ural</CountryID>
                <CountryID>Yakutsk</CountryID>
            </countries>
        </Continent>
        <Continent>
            <continentName>Australia</continentName>
            <bonusForHoldingContinent>2</bonusForHoldingContinent>
            <countries>
                <CountryID>EasternAustralia</CountryID>
                <CountryID>Indonesia</CountryID>
                <CountryID>NewGuinea</CountryID>
                <CountryID>WesternAustralia</CountryID>
            </countries>
        </Continent>
    </Continents>
</map>
